{
  "website": "http://www.cca.qc.ca/",
  "meta_description": "The Canadian Centre for Architecture (CCA) is an international research institution operating from the fundamental premise that architecture is a public concern.",
  "hours_url": "http://www.cca.qc.ca/en/visit-us",
  "tickets_url": "http://www.cca.qc.ca/en/visit-us",
  "accessibility_url": null,
  "hours_text": "",
  "admission_text": "",
  "accessibility_text": null,
  "collections_text": "# Space Half Empty\n\n## Maroš Krivý traces how photography frames the potentiality of wastelands\n\n“There is no such thing as an empty space,” my doctoral supervisor would quickly remind me anytime I brought up the topic of urban voids or wastelands. She was correct, of course. There is no empty space in capitalist economies, only processes of accumulation and devaluation through which capital is funneled into infrastructure and the built environment, then abandoned in pursuit of further accumulation. Emptiness mystifies—to claim that a place is empty ignores or obscures processes, conflicts, or histories through which it became such—and therefore justifies remaking the world in the image of capital, similar to how colonial expansion is premised on “improving” conquered territories. What capitalists and settlers share is their view of the world as a succession of retreating frontiers to be claimed. Yet what I was clumsily trying to get at was the significance of the wasteland as a historical category. For example, the wasteland has been understood both in terms of its landed relations and as a way of seeing space in terms of underlying interests in its use and development.1 In other words, emptiness can figure a tangible “social imaginary” to organize visions for the future: devoid of opportunities for some, full of promise for others. Considered in terms of spatial politics, emptiness is best approached historically as a category that justifies the imposition of values or func...",
  "from_wayback": false,
  "error": null,
  "fetched_at": "2026-01-17T22:58:18Z"
}
