{
  "museum_id": "usa-co-grand-junction-western-colorado-center-for-the-arts",
  "tour_planning_scores": {
    "contemporary_score": 6,
    "modern_score": 5,
    "impressionist_score": null,
    "expressionist_score": null,
    "classical_score": null,
    "american_art_score": 5,
    "european_art_score": null,
    "asian_art_score": null,
    "african_art_score": null,
    "painting_score": 6,
    "sculpture_score": 5,
    "decorative_arts_score": null,
    "photography_score": null,
    "collection_depth": 5,
    "collection_quality": 5,
    "exhibition_frequency": 6,
    "family_friendly_score": 7,
    "educational_value_score": 7,
    "architecture_score": 5,
    "scoring_rationale": "The Western Colorado Center for the Arts offers a moderate representation of contemporary and modern art, with a strong focus on community engagement and educational programs. The center's exhibitions are frequently updated, making it a dynamic cultural destination."
  },
  "curatorial_approach": null,
  "generated_at": "2023-10-01T00:00:00"
}
