{
  "state": "Kentucky",
  "state_code": "KY",
  "last_updated": "2026-01-16T04:15:36Z",
  "museums": [
    {
      "museum_id": "usa-ky-unknown-asia-institute-crane-house",
      "country": "USA",
      "state_province": "Kentucky",
      "city": "Unknown",
      "museum_name": "Asia Institute – Crane House",
      "alternate_names": null,
      "website": "http://www.cranehouse.org/",
      "status": "unknown",
      "last_updated": "2026-01-16",
      "street_address": "TBD",
      "address_line2": null,
      "postal_code": "TBD",
      "latitude": null,
      "longitude": null,
      "place_id": null,
      "address_source": "unknown",
      "address_last_verified": null,
      "museum_type": "Unknown",
      "primary_domain": null,
      "topics": null,
      "audience_focus": null,
      "open_hours_url": null,
      "tickets_url": null,
      "reservation_required": null,
      "accessibility_url": null,
      "reputation": null,
      "collection_tier": null,
      "time_needed": "Half day",
      "estimated_visit_minutes": null,
      "best_season": null,
      "nearby_museum_count": null,
      "visit_priority_notes": null,
      "parking_notes": null,
      "public_transit_notes": null,
      "impressionist_strength": null,
      "modern_contemporary_strength": null,
      "primary_art": null,
      "historical_context_score": null,
      "priority_score": null,
      "scoring_version": null,
      "scored_by": null,
      "score_notes": null,
      "score_last_verified": null,
      "data_sources": [
        "walker_reciprocal"
      ],
      "confidence": null,
      "row_notes_internal": "Seeded from walker-reciprocal roster; needs enrichment.; Wikidata: no search results; Nominatim: no results; MRD: computed city_tier=3 for Unknown; MRD: inferred time_needed='Half day (2-4 hours)' from museum_type; Official site: blocked by robots.txt; Wikidata: no search results; Nominatim: no results; MRD: normalized time_needed 'Half day (2-4 hours)' -> 'Half day'; Official site: blocked by robots.txt",
      "created_at": "2026-01-15",
      "updated_at": "2026-01-16",
      "notes": null,
      "city_tier": 3
    },
    {
      "museum_id": "usa-ky-unknown-behringer-crawford-museum",
      "country": "USA",
      "state_province": "Kentucky",
      "city": "Unknown",
      "museum_name": "Behringer-Crawford Museum",
      "alternate_names": null,
      "website": "http://bcmuseum.org/",
      "status": "unknown",
      "last_updated": "2026-01-16",
      "street_address": "TBD",
      "address_line2": null,
      "postal_code": "TBD",
      "latitude": null,
      "longitude": null,
      "place_id": null,
      "address_source": "unknown",
      "address_last_verified": null,
      "museum_type": "Unknown",
      "primary_domain": null,
      "topics": null,
      "audience_focus": null,
      "open_hours_url": "http://bcmuseum.org/plan-your-visit/now-bcm",
      "tickets_url": "http://bcmuseum.org/plan-your-visit/hours-and-admission-prices",
      "reservation_required": null,
      "accessibility_url": null,
      "reputation": null,
      "collection_tier": null,
      "time_needed": "Half day",
      "estimated_visit_minutes": null,
      "best_season": null,
      "nearby_museum_count": null,
      "visit_priority_notes": null,
      "parking_notes": null,
      "public_transit_notes": null,
      "impressionist_strength": null,
      "modern_contemporary_strength": null,
      "primary_art": null,
      "historical_context_score": null,
      "priority_score": null,
      "scoring_version": null,
      "scored_by": null,
      "score_notes": null,
      "score_last_verified": null,
      "data_sources": [
        "walker_reciprocal",
        "official_website",
        "http://bcmuseum.org"
      ],
      "confidence": null,
      "row_notes_internal": "Seeded from walker-reciprocal roster; needs enrichment.; Wikidata: no search results; Nominatim: no results; MRD: computed city_tier=3 for Unknown; MRD: inferred time_needed='Half day (2-4 hours)' from museum_type; Official site: fetched homepage; Wikidata: no search results; Nominatim: no results; MRD: normalized time_needed 'Half day (2-4 hours)' -> 'Half day'; Official site: fetched homepage; Official site: no applicable fields to fill",
      "created_at": "2026-01-15",
      "updated_at": "2026-01-16",
      "notes": null,
      "city_tier": 3
    },
    {
      "museum_id": "usa-ky-unknown-janice-mason-art-museum",
      "country": "USA",
      "state_province": "Kentucky",
      "city": "Cadiz",
      "museum_name": "Janice Mason Art Museum",
      "alternate_names": null,
      "website": "http://www.jmam.org/",
      "status": "unknown",
      "last_updated": "2026-01-16",
      "street_address": "TBD",
      "address_line2": null,
      "postal_code": "TBD",
      "latitude": null,
      "longitude": null,
      "place_id": null,
      "address_source": "unknown",
      "address_last_verified": null,
      "museum_type": "Unknown",
      "primary_domain": "Art",
      "topics": null,
      "audience_focus": null,
      "open_hours_url": null,
      "tickets_url": "https://jmam.org/jmam-art-book-club/",
      "reservation_required": null,
      "accessibility_url": null,
      "reputation": null,
      "collection_tier": null,
      "time_needed": "Half day",
      "estimated_visit_minutes": null,
      "best_season": null,
      "nearby_museum_count": null,
      "visit_priority_notes": null,
      "parking_notes": null,
      "public_transit_notes": null,
      "impressionist_strength": null,
      "modern_contemporary_strength": null,
      "primary_art": null,
      "historical_context_score": null,
      "priority_score": null,
      "scoring_version": null,
      "scored_by": null,
      "score_notes": null,
      "score_last_verified": null,
      "data_sources": [
        "walker_reciprocal",
        "official_website",
        "http://www.jmam.org"
      ],
      "confidence": null,
      "row_notes_internal": "Seeded from walker-reciprocal roster; needs enrichment.; Wikidata: no search results; Nominatim: no results; MRD: computed city_tier=3 for Unknown; MRD: inferred time_needed='Half day (2-4 hours)' from museum_type; Official site: fetched homepage; Official site: extracted city 'Cadiz' from page text; Inferred primary_domain=Art from name/type; Wikidata: no search results; Nominatim: no results; MRD: normalized time_needed 'Half day (2-4 hours)' -> 'Half day'; Official site: fetched homepage; Official site: no applicable fields to fill",
      "created_at": "2026-01-15",
      "updated_at": "2026-01-16",
      "notes": null,
      "city_tier": 3
    },
    {
      "museum_id": "usa-ky-unknown-kentucky-gateway-museum-center",
      "country": "USA",
      "state_province": "Kentucky",
      "city": "Maysville",
      "museum_name": "Kentucky Gateway Museum Center",
      "alternate_names": null,
      "website": "https://www.kygmc.org/",
      "status": "unknown",
      "last_updated": "2026-01-16",
      "street_address": "TBD",
      "address_line2": null,
      "postal_code": "41056",
      "latitude": 38.6482142,
      "longitude": -83.7670714,
      "place_id": null,
      "address_source": "unknown",
      "address_last_verified": null,
      "museum_type": "Unknown",
      "primary_domain": null,
      "topics": null,
      "audience_focus": null,
      "open_hours_url": "https://www.kygmc.org/visitkygmc",
      "tickets_url": "https://www.kygmc.org/visitkygmc",
      "reservation_required": null,
      "accessibility_url": null,
      "reputation": null,
      "collection_tier": null,
      "time_needed": "Half day",
      "estimated_visit_minutes": null,
      "best_season": null,
      "nearby_museum_count": null,
      "visit_priority_notes": null,
      "parking_notes": null,
      "public_transit_notes": null,
      "impressionist_strength": null,
      "modern_contemporary_strength": null,
      "primary_art": null,
      "historical_context_score": null,
      "priority_score": null,
      "scoring_version": null,
      "scored_by": null,
      "score_notes": null,
      "score_last_verified": null,
      "data_sources": [
        "walker_reciprocal",
        "official_website",
        "https://www.kygmc.org",
        "openstreetmap"
      ],
      "confidence": null,
      "row_notes_internal": "Seeded from walker-reciprocal roster; needs enrichment.; Wikidata: no search results; Nominatim: no results; MRD: computed city_tier=3 for Unknown; MRD: inferred time_needed='Half day (2-4 hours)' from museum_type; Official site: fetched homepage; Official site: extracted city 'Maysville' from page text; Wikidata: no search results; Nominatim: matched 1 result; MRD: normalized time_needed 'Half day (2-4 hours)' -> 'Half day'; Official site: fetched homepage; Official site: no applicable fields to fill",
      "created_at": "2026-01-15",
      "updated_at": "2026-01-16",
      "notes": null,
      "city_tier": 3
    },
    {
      "museum_id": "usa-ky-unknown-speed-art-museum",
      "country": "USA",
      "state_province": "Kentucky",
      "city": "Louisville",
      "museum_name": "Speed Art Museum",
      "alternate_names": null,
      "website": "http://www.speedmuseum.org/",
      "status": "unknown",
      "last_updated": "2026-01-16",
      "street_address": "TBD",
      "address_line2": null,
      "postal_code": "40208",
      "latitude": 38.2178538,
      "longitude": -85.7607957,
      "place_id": null,
      "address_source": "unknown",
      "address_last_verified": null,
      "museum_type": "Unknown",
      "primary_domain": "Art",
      "topics": null,
      "audience_focus": null,
      "open_hours_url": null,
      "tickets_url": null,
      "reservation_required": null,
      "accessibility_url": null,
      "reputation": null,
      "collection_tier": null,
      "time_needed": "Half day",
      "estimated_visit_minutes": null,
      "best_season": null,
      "nearby_museum_count": null,
      "visit_priority_notes": null,
      "parking_notes": null,
      "public_transit_notes": null,
      "impressionist_strength": null,
      "modern_contemporary_strength": null,
      "primary_art": null,
      "historical_context_score": null,
      "priority_score": null,
      "scoring_version": null,
      "scored_by": null,
      "score_notes": null,
      "score_last_verified": null,
      "data_sources": [
        "walker_reciprocal",
        "openstreetmap"
      ],
      "confidence": null,
      "row_notes_internal": "Seeded from walker-reciprocal roster; needs enrichment.; Wikidata: no search results; Nominatim: no results; City extraction: found 'Louisville' from open data; MRD: computed city_tier=1 for Louisville; MRD: inferred time_needed='Half day (2-4 hours)' from museum_type; Official site: blocked by robots.txt; Inferred primary_domain=Art from name/type; Wikidata: no search results; Nominatim: matched 1 result; MRD: normalized time_needed 'Half day (2-4 hours)' -> 'Half day'; Official site: blocked by robots.txt",
      "created_at": "2026-01-15",
      "updated_at": "2026-01-16",
      "notes": null,
      "city_tier": 1
    },
    {
      "museum_id": "usa-ky-bowling-green-national-corvette-museum",
      "country": "USA",
      "state_province": "Kentucky",
      "city": "Bowling Green",
      "museum_name": "National Corvette Museum",
      "alternate_names": null,
      "website": "http://www.corvettemuseum.org/",
      "status": "unknown",
      "last_updated": "2026-01-16",
      "street_address": "TBD",
      "address_line2": null,
      "postal_code": "42101",
      "latitude": 37.0042236,
      "longitude": -86.3744523,
      "place_id": null,
      "address_source": "unknown",
      "address_last_verified": null,
      "museum_type": "Unknown",
      "primary_domain": null,
      "topics": null,
      "audience_focus": null,
      "open_hours_url": null,
      "tickets_url": null,
      "reservation_required": null,
      "accessibility_url": null,
      "reputation": null,
      "collection_tier": null,
      "time_needed": "Half day",
      "estimated_visit_minutes": null,
      "best_season": null,
      "nearby_museum_count": null,
      "visit_priority_notes": null,
      "parking_notes": null,
      "public_transit_notes": null,
      "impressionist_strength": null,
      "modern_contemporary_strength": null,
      "primary_art": null,
      "historical_context_score": null,
      "priority_score": null,
      "scoring_version": null,
      "scored_by": null,
      "score_notes": null,
      "score_last_verified": null,
      "data_sources": [
        "walker_reciprocal",
        "openstreetmap"
      ],
      "confidence": null,
      "row_notes_internal": "Seeded from walker-reciprocal roster; needs enrichment.; Wikidata: no search results; Nominatim: matched 1 result; MRD: computed city_tier=2 for Bowling Green; MRD: inferred time_needed='Half day (2-4 hours)' from museum_type; Official site: blocked by robots.txt; Wikidata: no search results; Nominatim: matched 1 result; Nominatim: no applicable fields to fill; MRD: normalized time_needed 'Half day (2-4 hours)' -> 'Half day'; Official site: blocked by robots.txt",
      "created_at": "2026-01-15",
      "updated_at": "2026-01-16",
      "notes": null,
      "city_tier": 2
    },
    {
      "museum_id": "usa-ky-lexington-university-of-kentucky-art-museum",
      "country": "USA",
      "state_province": "Kentucky",
      "city": "Lexington",
      "museum_name": "University of Kentucky Art Museum",
      "alternate_names": null,
      "website": "http://www.uky.edu/ArtMuseum",
      "status": "unknown",
      "last_updated": "2026-01-16",
      "street_address": "TBD",
      "address_line2": null,
      "postal_code": "TBD",
      "latitude": null,
      "longitude": null,
      "place_id": null,
      "address_source": "unknown",
      "address_last_verified": null,
      "museum_type": "Unknown",
      "primary_domain": "Art",
      "topics": null,
      "audience_focus": null,
      "open_hours_url": null,
      "tickets_url": null,
      "reservation_required": null,
      "accessibility_url": null,
      "reputation": null,
      "collection_tier": null,
      "time_needed": "Half day",
      "estimated_visit_minutes": null,
      "best_season": null,
      "nearby_museum_count": null,
      "visit_priority_notes": null,
      "parking_notes": null,
      "public_transit_notes": null,
      "impressionist_strength": null,
      "modern_contemporary_strength": null,
      "primary_art": null,
      "historical_context_score": null,
      "priority_score": null,
      "scoring_version": null,
      "scored_by": null,
      "score_notes": null,
      "score_last_verified": null,
      "data_sources": [
        "walker_reciprocal",
        "official_website",
        "http://www.uky.edu/ArtMuseum"
      ],
      "confidence": null,
      "row_notes_internal": "Seeded from walker-reciprocal roster; needs enrichment.; Wikidata: no search results; Nominatim: no results; MRD: computed city_tier=2 for Lexington; MRD: inferred time_needed='Half day (2-4 hours)' from museum_type; Official site: Network error accessing http://www.uky.edu/ArtMuseum: [WinError 10054] An existing connection was forcibly closed by the remote host; Inferred primary_domain=Art from name/type; Wikidata: no search results; Nominatim: no results; MRD: normalized time_needed 'Half day (2-4 hours)' -> 'Half day'; Official site: Network error accessing http://www.uky.edu/ArtMuseum: [WinError 10054] An existing connection was forcibly closed by the remote host",
      "created_at": "2026-01-15",
      "updated_at": "2026-01-16",
      "notes": null,
      "city_tier": 2
    },
    {
      "museum_id": "usa-ky-louisville-frazier-international-history-museum",
      "country": "USA",
      "state_province": "Kentucky",
      "city": "Louisville",
      "museum_name": "Frazier International History Museum",
      "alternate_names": null,
      "website": "http://www.fraziermuseum.org/",
      "status": "unknown",
      "last_updated": "2026-01-16",
      "street_address": "829 West",
      "address_line2": null,
      "postal_code": "40202",
      "latitude": 38.2578961,
      "longitude": -85.7644884,
      "place_id": null,
      "address_source": "official_website",
      "address_last_verified": "2026-01-15",
      "museum_type": "Unknown",
      "primary_domain": "History",
      "topics": null,
      "audience_focus": null,
      "open_hours_url": "http://www.fraziermuseum.org/visitor-information",
      "tickets_url": "http://www.fraziermuseum.org/buy-tickets",
      "reservation_required": null,
      "accessibility_url": "https://fraziermuseum.org/deai-statement",
      "reputation": null,
      "collection_tier": null,
      "time_needed": "Half day",
      "estimated_visit_minutes": null,
      "best_season": null,
      "nearby_museum_count": null,
      "visit_priority_notes": null,
      "parking_notes": null,
      "public_transit_notes": null,
      "impressionist_strength": null,
      "modern_contemporary_strength": null,
      "primary_art": null,
      "historical_context_score": null,
      "priority_score": null,
      "scoring_version": null,
      "scored_by": null,
      "score_notes": null,
      "score_last_verified": null,
      "data_sources": [
        "walker_reciprocal",
        "official_website",
        "http://www.fraziermuseum.org"
      ],
      "confidence": null,
      "row_notes_internal": "Seeded from walker-reciprocal roster; needs enrichment.; Wikidata: no search results; Nominatim: no results; MRD: computed city_tier=1 for Louisville; MRD: inferred time_needed='Half day (2-4 hours)' from museum_type; Official site: fetched homepage; Official site: extracted full address from page text; Inferred primary_domain=History from name/type; Wikidata: no search results; Nominatim: no results; MRD: normalized time_needed 'Half day (2-4 hours)' -> 'Half day'; Official site: fetched homepage; Official site: no applicable fields to fill",
      "created_at": "2026-01-15",
      "updated_at": "2026-01-16",
      "notes": null,
      "city_tier": 1
    },
    {
      "museum_id": "usa-ky-paducah-yeiser-art-center",
      "country": "USA",
      "state_province": "Kentucky",
      "city": "Paducah",
      "museum_name": "Yeiser Art Center",
      "alternate_names": null,
      "website": "http://www.theyeiser.org/",
      "status": "unknown",
      "last_updated": "2026-01-16",
      "street_address": "TBD",
      "address_line2": null,
      "postal_code": "TBD",
      "latitude": null,
      "longitude": null,
      "place_id": null,
      "address_source": "unknown",
      "address_last_verified": null,
      "museum_type": "Unknown",
      "primary_domain": "Art",
      "topics": null,
      "audience_focus": null,
      "open_hours_url": null,
      "tickets_url": "https://www.facebook.com/yeiserartcenter",
      "reservation_required": null,
      "accessibility_url": null,
      "reputation": null,
      "collection_tier": null,
      "time_needed": "Half day",
      "estimated_visit_minutes": null,
      "best_season": null,
      "nearby_museum_count": null,
      "visit_priority_notes": null,
      "parking_notes": null,
      "public_transit_notes": null,
      "impressionist_strength": null,
      "modern_contemporary_strength": null,
      "primary_art": null,
      "historical_context_score": null,
      "priority_score": null,
      "scoring_version": null,
      "scored_by": null,
      "score_notes": null,
      "score_last_verified": null,
      "data_sources": [
        "walker_reciprocal",
        "official_website",
        "http://www.theyeiser.org"
      ],
      "confidence": null,
      "row_notes_internal": "Seeded from walker-reciprocal roster; needs enrichment.; Wikidata: no search results; Nominatim: no results; MRD: computed city_tier=3 for Paducah; MRD: inferred time_needed='Half day (2-4 hours)' from museum_type; Official site: fetched homepage; Inferred primary_domain=Art from name/type; Wikidata: no search results; Nominatim: no results; MRD: normalized time_needed 'Half day (2-4 hours)' -> 'Half day'; Official site: fetched homepage; Official site: no applicable fields to fill",
      "created_at": "2026-01-15",
      "updated_at": "2026-01-16",
      "notes": null,
      "city_tier": 3
    },
    {
      "museum_id": "usa-ky-paris-hopewell-museum-historic-paris-bourbon-county",
      "country": "USA",
      "state_province": "Kentucky",
      "city": "Paris",
      "museum_name": "Hopewell Museum/Historic Paris Bourbon County",
      "alternate_names": null,
      "website": "http://www.hopewellmuseum.org/",
      "status": "unknown",
      "last_updated": "2026-01-16",
      "street_address": "800 Pleasant St",
      "address_line2": null,
      "postal_code": "40361",
      "latitude": null,
      "longitude": null,
      "place_id": null,
      "address_source": "official_website",
      "address_last_verified": "2026-01-15",
      "museum_type": "Unknown",
      "primary_domain": "History",
      "topics": null,
      "audience_focus": null,
      "open_hours_url": "http://www.hopewellmuseum.org/visit/vault-store-online/my-cart/",
      "tickets_url": "https://www.facebook.com/HopewellMuseum",
      "reservation_required": null,
      "accessibility_url": null,
      "reputation": null,
      "collection_tier": null,
      "time_needed": "Half day",
      "estimated_visit_minutes": null,
      "best_season": null,
      "nearby_museum_count": null,
      "visit_priority_notes": null,
      "parking_notes": null,
      "public_transit_notes": null,
      "impressionist_strength": null,
      "modern_contemporary_strength": null,
      "primary_art": null,
      "historical_context_score": null,
      "priority_score": null,
      "scoring_version": null,
      "scored_by": null,
      "score_notes": null,
      "score_last_verified": null,
      "data_sources": [
        "walker_reciprocal",
        "official_website",
        "http://www.hopewellmuseum.org"
      ],
      "confidence": null,
      "row_notes_internal": "Seeded from walker-reciprocal roster; needs enrichment.; Wikidata: no search results; Nominatim: no results; MRD: computed city_tier=3 for Paris; MRD: inferred time_needed='Half day (2-4 hours)' from museum_type; Official site: fetched homepage; Official site: extracted full address from page text; Inferred primary_domain=History from name/type; Wikidata: no search results; Nominatim: no results; MRD: normalized time_needed 'Half day (2-4 hours)' -> 'Half day'; Official site: fetched homepage; Official site: no applicable fields to fill",
      "created_at": "2026-01-15",
      "updated_at": "2026-01-16",
      "notes": null,
      "city_tier": 3
    }
  ]
}
