{
  "state": "Kentucky",
  "state_code": "KY",
  "last_updated": "2026-01-15T17:22:19Z",
  "museums": [
    {
      "museum_id": "usa-ky-unknown-asia-institute-crane-house",
      "country": "USA",
      "state_province": "Kentucky",
      "city": "Unknown",
      "museum_name": "Asia Institute – Crane House",
      "alternate_names": null,
      "website": "http://www.cranehouse.org/",
      "status": "unknown",
      "last_updated": "2026-01-15",
      "street_address": "TBD",
      "address_line2": null,
      "postal_code": "TBD",
      "latitude": null,
      "longitude": null,
      "place_id": null,
      "address_source": "unknown",
      "address_last_verified": null,
      "museum_type": "Unknown",
      "primary_domain": null,
      "topics": null,
      "audience_focus": null,
      "open_hours_url": null,
      "tickets_url": null,
      "reservation_required": null,
      "accessibility_url": null,
      "reputation": null,
      "collection_tier": null,
      "time_needed": null,
      "estimated_visit_minutes": null,
      "best_season": null,
      "nearby_museum_count": null,
      "visit_priority_notes": null,
      "parking_notes": null,
      "public_transit_notes": null,
      "impressionist_strength": null,
      "modern_contemporary_strength": null,
      "primary_art": null,
      "historical_context_score": null,
      "priority_score": null,
      "scoring_version": null,
      "scored_by": null,
      "score_notes": null,
      "score_last_verified": null,
      "data_sources": [
        "walker_reciprocal"
      ],
      "confidence": null,
      "row_notes_internal": "Seeded from walker-reciprocal roster; needs enrichment.",
      "created_at": "2026-01-15",
      "updated_at": "2026-01-15",
      "notes": null
    },
    {
      "museum_id": "usa-ky-unknown-behringer-crawford-museum",
      "country": "USA",
      "state_province": "Kentucky",
      "city": "Unknown",
      "museum_name": "Behringer-Crawford Museum",
      "alternate_names": null,
      "website": "http://bcmuseum.org/",
      "status": "unknown",
      "last_updated": "2026-01-15",
      "street_address": "TBD",
      "address_line2": null,
      "postal_code": "TBD",
      "latitude": null,
      "longitude": null,
      "place_id": null,
      "address_source": "unknown",
      "address_last_verified": null,
      "museum_type": "Unknown",
      "primary_domain": null,
      "topics": null,
      "audience_focus": null,
      "open_hours_url": null,
      "tickets_url": null,
      "reservation_required": null,
      "accessibility_url": null,
      "reputation": null,
      "collection_tier": null,
      "time_needed": null,
      "estimated_visit_minutes": null,
      "best_season": null,
      "nearby_museum_count": null,
      "visit_priority_notes": null,
      "parking_notes": null,
      "public_transit_notes": null,
      "impressionist_strength": null,
      "modern_contemporary_strength": null,
      "primary_art": null,
      "historical_context_score": null,
      "priority_score": null,
      "scoring_version": null,
      "scored_by": null,
      "score_notes": null,
      "score_last_verified": null,
      "data_sources": [
        "walker_reciprocal"
      ],
      "confidence": null,
      "row_notes_internal": "Seeded from walker-reciprocal roster; needs enrichment.",
      "created_at": "2026-01-15",
      "updated_at": "2026-01-15",
      "notes": null
    },
    {
      "museum_id": "usa-ky-unknown-janice-mason-art-museum",
      "country": "USA",
      "state_province": "Kentucky",
      "city": "Unknown",
      "museum_name": "Janice Mason Art Museum",
      "alternate_names": null,
      "website": "http://www.jmam.org/",
      "status": "unknown",
      "last_updated": "2026-01-15",
      "street_address": "TBD",
      "address_line2": null,
      "postal_code": "TBD",
      "latitude": null,
      "longitude": null,
      "place_id": null,
      "address_source": "unknown",
      "address_last_verified": null,
      "museum_type": "Unknown",
      "primary_domain": null,
      "topics": null,
      "audience_focus": null,
      "open_hours_url": null,
      "tickets_url": null,
      "reservation_required": null,
      "accessibility_url": null,
      "reputation": null,
      "collection_tier": null,
      "time_needed": null,
      "estimated_visit_minutes": null,
      "best_season": null,
      "nearby_museum_count": null,
      "visit_priority_notes": null,
      "parking_notes": null,
      "public_transit_notes": null,
      "impressionist_strength": null,
      "modern_contemporary_strength": null,
      "primary_art": null,
      "historical_context_score": null,
      "priority_score": null,
      "scoring_version": null,
      "scored_by": null,
      "score_notes": null,
      "score_last_verified": null,
      "data_sources": [
        "walker_reciprocal"
      ],
      "confidence": null,
      "row_notes_internal": "Seeded from walker-reciprocal roster; needs enrichment.",
      "created_at": "2026-01-15",
      "updated_at": "2026-01-15",
      "notes": null
    },
    {
      "museum_id": "usa-ky-unknown-kentucky-gateway-museum-center",
      "country": "USA",
      "state_province": "Kentucky",
      "city": "Unknown",
      "museum_name": "Kentucky Gateway Museum Center",
      "alternate_names": null,
      "website": "https://www.kygmc.org/",
      "status": "unknown",
      "last_updated": "2026-01-15",
      "street_address": "TBD",
      "address_line2": null,
      "postal_code": "TBD",
      "latitude": null,
      "longitude": null,
      "place_id": null,
      "address_source": "unknown",
      "address_last_verified": null,
      "museum_type": "Unknown",
      "primary_domain": null,
      "topics": null,
      "audience_focus": null,
      "open_hours_url": null,
      "tickets_url": null,
      "reservation_required": null,
      "accessibility_url": null,
      "reputation": null,
      "collection_tier": null,
      "time_needed": null,
      "estimated_visit_minutes": null,
      "best_season": null,
      "nearby_museum_count": null,
      "visit_priority_notes": null,
      "parking_notes": null,
      "public_transit_notes": null,
      "impressionist_strength": null,
      "modern_contemporary_strength": null,
      "primary_art": null,
      "historical_context_score": null,
      "priority_score": null,
      "scoring_version": null,
      "scored_by": null,
      "score_notes": null,
      "score_last_verified": null,
      "data_sources": [
        "walker_reciprocal"
      ],
      "confidence": null,
      "row_notes_internal": "Seeded from walker-reciprocal roster; needs enrichment.",
      "created_at": "2026-01-15",
      "updated_at": "2026-01-15",
      "notes": null
    },
    {
      "museum_id": "usa-ky-unknown-speed-art-museum",
      "country": "USA",
      "state_province": "Kentucky",
      "city": "Unknown",
      "museum_name": "Speed Art Museum",
      "alternate_names": null,
      "website": "http://www.speedmuseum.org/",
      "status": "unknown",
      "last_updated": "2026-01-15",
      "street_address": "TBD",
      "address_line2": null,
      "postal_code": "TBD",
      "latitude": null,
      "longitude": null,
      "place_id": null,
      "address_source": "unknown",
      "address_last_verified": null,
      "museum_type": "Unknown",
      "primary_domain": null,
      "topics": null,
      "audience_focus": null,
      "open_hours_url": null,
      "tickets_url": null,
      "reservation_required": null,
      "accessibility_url": null,
      "reputation": null,
      "collection_tier": null,
      "time_needed": null,
      "estimated_visit_minutes": null,
      "best_season": null,
      "nearby_museum_count": null,
      "visit_priority_notes": null,
      "parking_notes": null,
      "public_transit_notes": null,
      "impressionist_strength": null,
      "modern_contemporary_strength": null,
      "primary_art": null,
      "historical_context_score": null,
      "priority_score": null,
      "scoring_version": null,
      "scored_by": null,
      "score_notes": null,
      "score_last_verified": null,
      "data_sources": [
        "walker_reciprocal"
      ],
      "confidence": null,
      "row_notes_internal": "Seeded from walker-reciprocal roster; needs enrichment.",
      "created_at": "2026-01-15",
      "updated_at": "2026-01-15",
      "notes": null
    },
    {
      "museum_id": "usa-ky-bowling-green-national-corvette-museum",
      "country": "USA",
      "state_province": "Kentucky",
      "city": "Bowling Green",
      "museum_name": "National Corvette Museum",
      "alternate_names": null,
      "website": "http://www.corvettemuseum.org/",
      "status": "unknown",
      "last_updated": "2026-01-15",
      "street_address": "TBD",
      "address_line2": null,
      "postal_code": "TBD",
      "latitude": null,
      "longitude": null,
      "place_id": null,
      "address_source": "unknown",
      "address_last_verified": null,
      "museum_type": "Unknown",
      "primary_domain": null,
      "topics": null,
      "audience_focus": null,
      "open_hours_url": null,
      "tickets_url": null,
      "reservation_required": null,
      "accessibility_url": null,
      "reputation": null,
      "collection_tier": null,
      "time_needed": null,
      "estimated_visit_minutes": null,
      "best_season": null,
      "nearby_museum_count": null,
      "visit_priority_notes": null,
      "parking_notes": null,
      "public_transit_notes": null,
      "impressionist_strength": null,
      "modern_contemporary_strength": null,
      "primary_art": null,
      "historical_context_score": null,
      "priority_score": null,
      "scoring_version": null,
      "scored_by": null,
      "score_notes": null,
      "score_last_verified": null,
      "data_sources": [
        "walker_reciprocal"
      ],
      "confidence": null,
      "row_notes_internal": "Seeded from walker-reciprocal roster; needs enrichment.",
      "created_at": "2026-01-15",
      "updated_at": "2026-01-15",
      "notes": null
    },
    {
      "museum_id": "usa-ky-lexington-university-of-kentucky-art-museum",
      "country": "USA",
      "state_province": "Kentucky",
      "city": "Lexington",
      "museum_name": "University of Kentucky Art Museum",
      "alternate_names": null,
      "website": "http://www.uky.edu/ArtMuseum",
      "status": "unknown",
      "last_updated": "2026-01-15",
      "street_address": "TBD",
      "address_line2": null,
      "postal_code": "TBD",
      "latitude": null,
      "longitude": null,
      "place_id": null,
      "address_source": "unknown",
      "address_last_verified": null,
      "museum_type": "Unknown",
      "primary_domain": null,
      "topics": null,
      "audience_focus": null,
      "open_hours_url": null,
      "tickets_url": null,
      "reservation_required": null,
      "accessibility_url": null,
      "reputation": null,
      "collection_tier": null,
      "time_needed": null,
      "estimated_visit_minutes": null,
      "best_season": null,
      "nearby_museum_count": null,
      "visit_priority_notes": null,
      "parking_notes": null,
      "public_transit_notes": null,
      "impressionist_strength": null,
      "modern_contemporary_strength": null,
      "primary_art": null,
      "historical_context_score": null,
      "priority_score": null,
      "scoring_version": null,
      "scored_by": null,
      "score_notes": null,
      "score_last_verified": null,
      "data_sources": [
        "walker_reciprocal"
      ],
      "confidence": null,
      "row_notes_internal": "Seeded from walker-reciprocal roster; needs enrichment.",
      "created_at": "2026-01-15",
      "updated_at": "2026-01-15",
      "notes": null
    },
    {
      "museum_id": "usa-ky-louisville-frazier-international-history-museum",
      "country": "USA",
      "state_province": "Kentucky",
      "city": "Louisville",
      "museum_name": "Frazier International History Museum",
      "alternate_names": null,
      "website": "http://www.fraziermuseum.org/",
      "status": "unknown",
      "last_updated": "2026-01-15",
      "street_address": "TBD",
      "address_line2": null,
      "postal_code": "TBD",
      "latitude": null,
      "longitude": null,
      "place_id": null,
      "address_source": "unknown",
      "address_last_verified": null,
      "museum_type": "Unknown",
      "primary_domain": null,
      "topics": null,
      "audience_focus": null,
      "open_hours_url": null,
      "tickets_url": null,
      "reservation_required": null,
      "accessibility_url": null,
      "reputation": null,
      "collection_tier": null,
      "time_needed": null,
      "estimated_visit_minutes": null,
      "best_season": null,
      "nearby_museum_count": null,
      "visit_priority_notes": null,
      "parking_notes": null,
      "public_transit_notes": null,
      "impressionist_strength": null,
      "modern_contemporary_strength": null,
      "primary_art": null,
      "historical_context_score": null,
      "priority_score": null,
      "scoring_version": null,
      "scored_by": null,
      "score_notes": null,
      "score_last_verified": null,
      "data_sources": [
        "walker_reciprocal"
      ],
      "confidence": null,
      "row_notes_internal": "Seeded from walker-reciprocal roster; needs enrichment.",
      "created_at": "2026-01-15",
      "updated_at": "2026-01-15",
      "notes": null
    },
    {
      "museum_id": "usa-ky-paducah-yeiser-art-center",
      "country": "USA",
      "state_province": "Kentucky",
      "city": "Paducah",
      "museum_name": "Yeiser Art Center",
      "alternate_names": null,
      "website": "http://www.theyeiser.org/",
      "status": "unknown",
      "last_updated": "2026-01-15",
      "street_address": "TBD",
      "address_line2": null,
      "postal_code": "TBD",
      "latitude": null,
      "longitude": null,
      "place_id": null,
      "address_source": "unknown",
      "address_last_verified": null,
      "museum_type": "Unknown",
      "primary_domain": null,
      "topics": null,
      "audience_focus": null,
      "open_hours_url": null,
      "tickets_url": null,
      "reservation_required": null,
      "accessibility_url": null,
      "reputation": null,
      "collection_tier": null,
      "time_needed": null,
      "estimated_visit_minutes": null,
      "best_season": null,
      "nearby_museum_count": null,
      "visit_priority_notes": null,
      "parking_notes": null,
      "public_transit_notes": null,
      "impressionist_strength": null,
      "modern_contemporary_strength": null,
      "primary_art": null,
      "historical_context_score": null,
      "priority_score": null,
      "scoring_version": null,
      "scored_by": null,
      "score_notes": null,
      "score_last_verified": null,
      "data_sources": [
        "walker_reciprocal"
      ],
      "confidence": null,
      "row_notes_internal": "Seeded from walker-reciprocal roster; needs enrichment.",
      "created_at": "2026-01-15",
      "updated_at": "2026-01-15",
      "notes": null
    },
    {
      "museum_id": "usa-ky-paris-hopewell-museum-historic-paris-bourbon-county",
      "country": "USA",
      "state_province": "Kentucky",
      "city": "Paris",
      "museum_name": "Hopewell Museum/Historic Paris Bourbon County",
      "alternate_names": null,
      "website": "http://www.hopewellmuseum.org/",
      "status": "unknown",
      "last_updated": "2026-01-15",
      "street_address": "TBD",
      "address_line2": null,
      "postal_code": "TBD",
      "latitude": null,
      "longitude": null,
      "place_id": null,
      "address_source": "unknown",
      "address_last_verified": null,
      "museum_type": "Unknown",
      "primary_domain": null,
      "topics": null,
      "audience_focus": null,
      "open_hours_url": null,
      "tickets_url": null,
      "reservation_required": null,
      "accessibility_url": null,
      "reputation": null,
      "collection_tier": null,
      "time_needed": null,
      "estimated_visit_minutes": null,
      "best_season": null,
      "nearby_museum_count": null,
      "visit_priority_notes": null,
      "parking_notes": null,
      "public_transit_notes": null,
      "impressionist_strength": null,
      "modern_contemporary_strength": null,
      "primary_art": null,
      "historical_context_score": null,
      "priority_score": null,
      "scoring_version": null,
      "scored_by": null,
      "score_notes": null,
      "score_last_verified": null,
      "data_sources": [
        "walker_reciprocal"
      ],
      "confidence": null,
      "row_notes_internal": "Seeded from walker-reciprocal roster; needs enrichment.",
      "created_at": "2026-01-15",
      "updated_at": "2026-01-15",
      "notes": null
    }
  ]
}
