{
  "search_query": "Elliott Museum Stuart museum",
  "found": true,
  "page_title": "Elliott Museum",
  "page_url": "https://en.wikipedia.org/wiki/Elliott_Museum",
  "extract": "The Elliott Museum, located at 825 N.E. Ocean Blvd. on Hutchinson Island in Stuart, Florida, United States, focuses on art, history, and technology. Named after the prolific inventor Sterling Elliott, the museum features a changing exhibition gallery and an art studio; maritime, baseball, and local history galleries; and bicycles, classic wooden boats, motorcycles, over 90 cars and trucks, and even an airplane. Over 50 vehicles are displayed in a unique robotic racking system which retrieves vehicles on demand for display on a turntable. The Elliott Museum has one of the largest collections of historic Ford Model A and Model AA commercial vehicles in the world.",
  "error": null,
  "fetched_at": "2026-01-17T23:00:46Z"
}
